[ {
  "name" : "address",
  "sourceFieldname" : "address",
  "description" : "address",
  "dataType" : "string",
  "hasIndex" : false,
  "unique" : false,
  "primarykey" : false,
  "namefield" : false,
  "nullable" : true,
  "custom" : false,
  "createable" : true,
  "updateable" : true,
  "audit" : false,
  "customizable" : false,
  "fieldLength" : 180,
  "precision" : 0,
  "fieldOrder" : 0,
  "fieldProperties" : {
    "autoGenerated" : "false"
  },
  "etag" : "dc3779d0-70d4-4c15-a149-79fe5c713e5f",
  "isExtended" : false
}, {
  "name" : "adminFee",
  "sourceFieldname" : "adminFee",
  "description" : "adminFee",
  "dataType" : "string",
  "hasIndex" : false,
  "unique" : false,
  "primarykey" : false,
  "namefield" : false,
  "nullable" : true,
  "custom" : false,
  "createable" : true,
  "updateable" : true,
  "audit" : false,
  "customizable" : false,
  "fieldLength" : 10,
  "precision" : 0,
  "fieldOrder" : 0,
  "fieldProperties" : {
    "autoGenerated" : "false"
  },
  "etag" : "8441feba-880a-42ad-bc53-989bccae9518",
  "isExtended" : false
}, {
  "name" : "analysis",
  "sourceFieldname" : "analysis",
  "description" : "analysis",
  "dataType" : "string",
  "hasIndex" : false,
  "unique" : false,
  "primarykey" : false,
  "namefield" : false,
  "nullable" : true,
  "custom" : false,
  "createable" : true,
  "updateable" : true,
  "audit" : false,
  "customizable" : false,
  "fieldLength" : 256,
  "precision" : 0,
  "fieldOrder" : 0,
  "fieldProperties" : {
    "autoGenerated" : "false"
  },
  "etag" : "15ad05ad-8eeb-4908-a12a-17990ca4dc13",
  "isExtended" : false
}, {
  "name" : "bids",
  "sourceFieldname" : "bids",
  "description" : "bids",
  "dataType" : "number",
  "hasIndex" : false,
  "unique" : false,
  "primarykey" : false,
  "namefield" : false,
  "nullable" : true,
  "custom" : false,
  "createable" : true,
  "updateable" : true,
  "audit" : false,
  "customizable" : false,
  "fieldLength" : 10,
  "precision" : 0,
  "fieldOrder" : 0,
  "fieldProperties" : {
    "autoGenerated" : "false"
  },
  "etag" : "a973764c-4058-4170-8e25-2a0edb087425",
  "isExtended" : false
}, {
  "name" : "chassis",
  "sourceFieldname" : "chassis",
  "description" : "chassis",
  "dataType" : "string",
  "hasIndex" : false,
  "unique" : false,
  "primarykey" : false,
  "namefield" : false,
  "nullable" : true,
  "custom" : false,
  "createable" : true,
  "updateable" : true,
  "audit" : false,
  "customizable" : false,
  "fieldLength" : 45,
  "precision" : 0,
  "fieldOrder" : 0,
  "fieldProperties" : {
    "autoGenerated" : "false"
  },
  "etag" : "ee39e51f-0d73-4e84-9fca-5c5232c81b33",
  "isExtended" : false
}, {
  "name" : "city",
  "sourceFieldname" : "city",
  "description" : "city",
  "dataType" : "string",
  "hasIndex" : false,
  "unique" : false,
  "primarykey" : false,
  "namefield" : false,
  "nullable" : true,
  "custom" : false,
  "createable" : true,
  "updateable" : true,
  "audit" : false,
  "customizable" : false,
  "fieldLength" : 45,
  "precision" : 0,
  "fieldOrder" : 0,
  "fieldProperties" : {
    "autoGenerated" : "false"
  },
  "etag" : "6066d4ff-024c-498e-8eec-bd7d54dd271f",
  "isExtended" : false
}, {
  "name" : "colour",
  "sourceFieldname" : "colour",
  "description" : "colour",
  "dataType" : "string",
  "hasIndex" : false,
  "unique" : false,
  "primarykey" : false,
  "namefield" : false,
  "nullable" : true,
  "custom" : false,
  "createable" : true,
  "updateable" : true,
  "audit" : false,
  "customizable" : false,
  "fieldLength" : 45,
  "precision" : 0,
  "fieldOrder" : 0,
  "fieldProperties" : {
    "autoGenerated" : "false"
  },
  "etag" : "153c3504-aad9-4fb0-bd02-e56fd520bfe0",
  "isExtended" : false
}, {
  "name" : "created",
  "sourceFieldname" : "created",
  "description" : "created",
  "dataType" : "date",
  "hasIndex" : false,
  "unique" : false,
  "primarykey" : false,
  "namefield" : false,
  "nullable" : true,
  "custom" : false,
  "createable" : true,
  "updateable" : true,
  "audit" : false,
  "customizable" : false,
  "fieldLength" : 19,
  "precision" : 0,
  "fieldOrder" : 0,
  "fieldProperties" : {
    "autoGenerated" : "false"
  },
  "etag" : "e5bb573f-c17f-47b6-b75e-1b6844c2e0f7",
  "isExtended" : false
}, {
  "name" : "cylinders",
  "sourceFieldname" : "cylinders",
  "description" : "cylinders",
  "dataType" : "number",
  "hasIndex" : false,
  "unique" : false,
  "primarykey" : false,
  "namefield" : false,
  "nullable" : true,
  "custom" : false,
  "createable" : true,
  "updateable" : true,
  "audit" : false,
  "customizable" : false,
  "fieldLength" : 10,
  "precision" : 0,
  "fieldOrder" : 0,
  "fieldProperties" : {
    "autoGenerated" : "false"
  },
  "etag" : "083de640-8a6e-4cb2-977b-238ff04b1118",
  "isExtended" : false
}, {
  "name" : "description",
  "sourceFieldname" : "description",
  "description" : "description",
  "dataType" : "string",
  "hasIndex" : false,
  "unique" : false,
  "primarykey" : false,
  "namefield" : false,
  "nullable" : true,
  "custom" : false,
  "createable" : true,
  "updateable" : true,
  "audit" : false,
  "customizable" : false,
  "fieldLength" : 2147483647,
  "precision" : 0,
  "fieldOrder" : 0,
  "fieldProperties" : {
    "autoGenerated" : "false"
  },
  "etag" : "14a4bcb2-9dbf-4cf9-af0a-54231f959565",
  "isExtended" : false
}, {
  "name" : "docDelivery",
  "sourceFieldname" : "docDelivery",
  "description" : "docDelivery",
  "dataType" : "string",
  "hasIndex" : false,
  "unique" : false,
  "primarykey" : false,
  "namefield" : false,
  "nullable" : true,
  "custom" : false,
  "createable" : true,
  "updateable" : true,
  "audit" : false,
  "customizable" : false,
  "fieldLength" : 10,
  "precision" : 0,
  "fieldOrder" : 0,
  "fieldProperties" : {
    "autoGenerated" : "false"
  },
  "etag" : "ec83af2f-c926-4bf2-a27f-557c23aefd1a",
  "isExtended" : false
}, {
  "name" : "doors",
  "sourceFieldname" : "doors",
  "description" : "doors",
  "dataType" : "number",
  "hasIndex" : false,
  "unique" : false,
  "primarykey" : false,
  "namefield" : false,
  "nullable" : true,
  "custom" : false,
  "createable" : true,
  "updateable" : true,
  "audit" : false,
  "customizable" : false,
  "fieldLength" : 10,
  "precision" : 0,
  "fieldOrder" : 0,
  "fieldProperties" : {
    "autoGenerated" : "false"
  },
  "etag" : "0b98c60c-5089-4556-9716-0ea8078efd78",
  "isExtended" : false
}, {
  "name" : "fuel",
  "sourceFieldname" : "fuel",
  "description" : "fuel",
  "dataType" : "string",
  "hasIndex" : false,
  "unique" : false,
  "primarykey" : false,
  "namefield" : false,
  "nullable" : true,
  "custom" : false,
  "createable" : true,
  "updateable" : true,
  "audit" : false,
  "customizable" : false,
  "fieldLength" : 20,
  "precision" : 0,
  "fieldOrder" : 0,
  "fieldProperties" : {
    "autoGenerated" : "false"
  },
  "etag" : "828b42b0-0f17-4a47-bc38-9f955e9ee3f8",
  "isExtended" : false
}, {
  "name" : "general",
  "sourceFieldname" : "general",
  "description" : "general",
  "dataType" : "string",
  "hasIndex" : false,
  "unique" : false,
  "primarykey" : false,
  "namefield" : false,
  "nullable" : true,
  "custom" : false,
  "createable" : true,
  "updateable" : true,
  "audit" : false,
  "customizable" : false,
  "fieldLength" : 180,
  "precision" : 0,
  "fieldOrder" : 0,
  "fieldProperties" : {
    "autoGenerated" : "false"
  },
  "etag" : "d90bcca2-5de8-4548-9bee-404b342a3a66",
  "isExtended" : false
}, {
  "name" : "latitude",
  "sourceFieldname" : "latitude",
  "description" : "latitude",
  "dataType" : "string",
  "hasIndex" : false,
  "unique" : false,
  "primarykey" : false,
  "namefield" : false,
  "nullable" : true,
  "custom" : false,
  "createable" : true,
  "updateable" : true,
  "audit" : false,
  "customizable" : false,
  "fieldLength" : 18,
  "precision" : 0,
  "fieldOrder" : 0,
  "fieldProperties" : {
    "autoGenerated" : "false"
  },
  "etag" : "df768b48-05c7-4c32-aacb-bb64b34f921f",
  "isExtended" : false
}, {
  "name" : "longitude",
  "sourceFieldname" : "longitude",
  "description" : "longitude",
  "dataType" : "string",
  "hasIndex" : false,
  "unique" : false,
  "primarykey" : false,
  "namefield" : false,
  "nullable" : true,
  "custom" : false,
  "createable" : true,
  "updateable" : true,
  "audit" : false,
  "customizable" : false,
  "fieldLength" : 18,
  "precision" : 0,
  "fieldOrder" : 0,
  "fieldProperties" : {
    "autoGenerated" : "false"
  },
  "etag" : "806814f9-1258-43f1-aa2a-b2a926046b5d",
  "isExtended" : false
}, {
  "name" : "make",
  "sourceFieldname" : "make",
  "description" : "make",
  "dataType" : "string",
  "hasIndex" : false,
  "unique" : false,
  "primarykey" : false,
  "namefield" : false,
  "nullable" : true,
  "custom" : false,
  "createable" : true,
  "updateable" : true,
  "audit" : false,
  "customizable" : false,
  "fieldLength" : 45,
  "precision" : 0,
  "fieldOrder" : 0,
  "fieldProperties" : {
    "autoGenerated" : "false"
  },
  "etag" : "583910b7-ace7-4b11-be86-70a9f8c2733b",
  "isExtended" : false
}, {
  "name" : "media",
  "sourceFieldname" : "media",
  "description" : "media",
  "dataType" : "string",
  "hasIndex" : false,
  "unique" : false,
  "primarykey" : false,
  "namefield" : false,
  "nullable" : true,
  "custom" : false,
  "createable" : true,
  "updateable" : true,
  "audit" : false,
  "customizable" : false,
  "fieldLength" : 180,
  "precision" : 0,
  "fieldOrder" : 0,
  "fieldProperties" : {
    "autoGenerated" : "false"
  },
  "etag" : "491291cc-0a0a-479e-a547-97b6e43b25cc",
  "isExtended" : false
}, {
  "name" : "millage",
  "sourceFieldname" : "millage",
  "description" : "millage",
  "dataType" : "number",
  "hasIndex" : false,
  "unique" : false,
  "primarykey" : false,
  "namefield" : false,
  "nullable" : true,
  "custom" : false,
  "createable" : true,
  "updateable" : true,
  "audit" : false,
  "customizable" : false,
  "fieldLength" : 19,
  "precision" : 0,
  "fieldOrder" : 0,
  "fieldProperties" : {
    "autoGenerated" : "false"
  },
  "etag" : "b1b1d018-4536-4e9a-b6ba-4871f8f6a5a3",
  "isExtended" : false
}, {
  "name" : "model",
  "sourceFieldname" : "model",
  "description" : "model",
  "dataType" : "string",
  "hasIndex" : false,
  "unique" : false,
  "primarykey" : false,
  "namefield" : false,
  "nullable" : true,
  "custom" : false,
  "createable" : true,
  "updateable" : true,
  "audit" : false,
  "customizable" : false,
  "fieldLength" : 45,
  "precision" : 0,
  "fieldOrder" : 0,
  "fieldProperties" : {
    "autoGenerated" : "false"
  },
  "etag" : "55367939-1e60-48ac-b350-d3043a58a845",
  "isExtended" : false
}, {
  "name" : "note",
  "sourceFieldname" : "note",
  "description" : "note",
  "dataType" : "string",
  "hasIndex" : false,
  "unique" : false,
  "primarykey" : false,
  "namefield" : false,
  "nullable" : true,
  "custom" : false,
  "createable" : true,
  "updateable" : true,
  "audit" : false,
  "customizable" : false,
  "fieldLength" : 2147483647,
  "precision" : 0,
  "fieldOrder" : 0,
  "fieldProperties" : {
    "autoGenerated" : "false"
  },
  "etag" : "f1f6ae11-43cf-479b-a68d-3aacc50ced2a",
  "isExtended" : false
}, {
  "name" : "power",
  "sourceFieldname" : "power",
  "description" : "power",
  "dataType" : "string",
  "hasIndex" : false,
  "unique" : false,
  "primarykey" : false,
  "namefield" : false,
  "nullable" : true,
  "custom" : false,
  "createable" : true,
  "updateable" : true,
  "audit" : false,
  "customizable" : false,
  "fieldLength" : 45,
  "precision" : 0,
  "fieldOrder" : 0,
  "fieldProperties" : {
    "autoGenerated" : "false"
  },
  "etag" : "6f501300-9767-426e-8b69-c58ff088d22b",
  "isExtended" : false
}, {
  "name" : "taxAdded",
  "sourceFieldname" : "taxAdded",
  "description" : "taxAdded",
  "dataType" : "string",
  "hasIndex" : false,
  "unique" : false,
  "primarykey" : false,
  "namefield" : false,
  "nullable" : true,
  "custom" : false,
  "createable" : true,
  "updateable" : true,
  "audit" : false,
  "customizable" : false,
  "fieldLength" : 10,
  "precision" : 0,
  "fieldOrder" : 0,
  "fieldProperties" : {
    "autoGenerated" : "false"
  },
  "etag" : "c40b5f0b-c974-4200-9701-6868b869704f",
  "isExtended" : false
}, {
  "name" : "transmission",
  "sourceFieldname" : "transmission",
  "description" : "transmission",
  "dataType" : "string",
  "hasIndex" : false,
  "unique" : false,
  "primarykey" : false,
  "namefield" : false,
  "nullable" : true,
  "custom" : false,
  "createable" : true,
  "updateable" : true,
  "audit" : false,
  "customizable" : false,
  "fieldLength" : 45,
  "precision" : 0,
  "fieldOrder" : 0,
  "fieldProperties" : {
    "autoGenerated" : "false"
  },
  "etag" : "50d8ce18-b3fa-45b5-b71e-393adfdf17a9",
  "isExtended" : false
}, {
  "name" : "type",
  "sourceFieldname" : "type",
  "description" : "type",
  "dataType" : "string",
  "hasIndex" : false,
  "unique" : false,
  "primarykey" : false,
  "namefield" : false,
  "nullable" : true,
  "custom" : false,
  "createable" : true,
  "updateable" : true,
  "audit" : false,
  "customizable" : false,
  "fieldLength" : 45,
  "precision" : 0,
  "fieldOrder" : 0,
  "fieldProperties" : {
    "autoGenerated" : "false"
  },
  "etag" : "7f41b657-1055-4572-9bbb-3757e0819315",
  "isExtended" : false
}, {
  "name" : "value",
  "sourceFieldname" : "value",
  "description" : "value",
  "dataType" : "number",
  "hasIndex" : false,
  "unique" : false,
  "primarykey" : false,
  "namefield" : false,
  "nullable" : true,
  "custom" : false,
  "createable" : true,
  "updateable" : true,
  "audit" : false,
  "customizable" : false,
  "fieldLength" : 19,
  "precision" : 0,
  "fieldOrder" : 0,
  "fieldProperties" : {
    "autoGenerated" : "false"
  },
  "etag" : "0e07a4aa-0384-433d-9cf6-ba8e0f21b7e7",
  "isExtended" : false
}, {
  "name" : "vehicleID",
  "sourceFieldname" : "vehicleID",
  "description" : "vehicleID",
  "dataType" : "string",
  "hasIndex" : false,
  "unique" : false,
  "primarykey" : true,
  "namefield" : false,
  "nullable" : false,
  "custom" : false,
  "createable" : true,
  "updateable" : false,
  "audit" : false,
  "customizable" : false,
  "fieldLength" : 8,
  "precision" : 0,
  "fieldOrder" : 0,
  "fieldProperties" : {
    "autoGenerated" : "false"
  },
  "etag" : "92b84949-c021-4f69-a963-c31fcb95b821",
  "isExtended" : false
}, {
  "name" : "vehicleName",
  "sourceFieldname" : "vehicleName",
  "description" : "vehicleName",
  "dataType" : "string",
  "hasIndex" : false,
  "unique" : false,
  "primarykey" : false,
  "namefield" : false,
  "nullable" : true,
  "custom" : false,
  "createable" : true,
  "updateable" : true,
  "audit" : false,
  "customizable" : false,
  "fieldLength" : 90,
  "precision" : 0,
  "fieldOrder" : 0,
  "fieldProperties" : {
    "autoGenerated" : "false"
  },
  "etag" : "f81e827d-0e4a-497f-8f98-d759c82dd38d",
  "isExtended" : false
}, {
  "name" : "year",
  "sourceFieldname" : "year",
  "description" : "year",
  "dataType" : "string",
  "hasIndex" : false,
  "unique" : false,
  "primarykey" : false,
  "namefield" : false,
  "nullable" : true,
  "custom" : false,
  "createable" : true,
  "updateable" : true,
  "audit" : false,
  "customizable" : false,
  "fieldLength" : 4,
  "precision" : 0,
  "fieldOrder" : 0,
  "fieldProperties" : {
    "autoGenerated" : "false"
  },
  "etag" : "6c920cf0-7793-4170-a50d-793013f489d2",
  "isExtended" : false
} ]